repeated_addition/controller.v
module controller(LdA, LdB, LdP, clrP, decB, done, clk, eqz, start);

	input clk, eqz, start;
	output reg LdA, LdB, LdP, clrP, decB, done;
	reg [2:0] state;

	parameter s0 = 3'b000, s1 = 3'b001, s2 = 3'b010, s3 = 3'b011, s4 = 3'b100;

	always @(posedge clk)
	begin
		case(state)
			s0: if (start) state <= s1;
			s1: state <= s2;
			s2: state <= s3;
			s3: #2 if (eqz) state <= s4;
			default: state <= s0;
		endcase
	end

	always @(state)
	begin
		case(state)
			s0: begin #1 LdA=0; LdB=0; LdP=0; clrP=0; decB=0; end
			s1: begin #1 LdA=1; end
			s2: begin #1 LdA=0; LdB=1; clrP=1; end
			s3: begin #1 LdB=0; LdP=1; clrP=0; decB=1; end
			s4: begin #1 done=1; LdB=0; LdP=0; decB=0; end
			default: begin #1 LdA=0; LdB=0; LdP=0; clrP=0;; decB=0; end
		endcase
	end
	
endmodule

repeated_addition/datapath.v
module MUL_datapath(eqz, LdA, LdB, LdP, clrP, decB, data_in, clk);

	input LdA, LdB, LdP, clrP, decB, clk;
	input [15:0] data_in;
	output eqz;
	wire [15:0] X, Y, Z, Bout, Bus;

  assign Bus = data_in;

	PIPO1 A(X, Bus, LdA, clk);
	PIPO2 P(Y, Z, LdP, clrP, clk);
	CNTR B(Bout, Bus, LdB, decB, clk);
	ADD AD(Z, X, Y);
	EQZ COMP(eqz, Bout);

endmodule

module PIPO1(dout, din, ld, clk);

	input [15:0] din;
	input ld, clk;
	output reg[15:0] dout;

	always @(posedge clk)
		if(ld) dout <= din;

endmodule

module PIPO2(dout, din, ld, clr, clk);

	input [15:0] din;
	input ld, clr, clk;
	output reg [15:0] dout;

	always @(posedge clk) begin
		if(clr) dout <= 16'b0;
		else if (ld) dout <= din;
	end

endmodule

module ADD(out, in1, in2);

	input[15:0] in1, in2;
	output reg [15:0] out;
	
	always @(*)
		out = in1 + in2;

endmodule

module EQZ(eqz, data);

	input [15:0] data; 
	output eqz;
	assign eqz = (data==0);

endmodule

module CNTR(dout, din, ld, dec, clk);

	input [15:0] din;
	input ld, dec,clk;
	output reg [15:0] dout;

	always @(posedge clk) begin
		if(ld) dout <= din;
		else if (dec) dout <= dout-1;
	end

endmodule

repeated_addition/testbench.v
module MUL_test;

	reg [15:0] data_in;
	reg clk, start;
	wire done;
	MUL_datapath DP(eqz, LdA, LdB, LdP, clrP, decB, data_in, clk);
	controller CON(LdA, LdB, LdP, clrP, decB, done, clk, eqz, start);

	initial
		begin
		clk = 1'b0;
		#3 start = 1'b1;
		#500 $finish;
	end

	always #5 clk = ~clk;

	initial begin
		#17 data_in = 17;
		#10 data_in = 5;
	end

	initial 
	begin
		$monitor($time, "%d %b", DP.Y, done);
		$dumpfile("tboutput.vcd");
		$dumpvars(0, MUL_test);
	end
	
endmodule

repeated_addition/tboutput.vcd
$date
	Thu Jun  5 11:17:29 2025
$end
$version
	Icarus Verilog
$end
$timescale
	1s
$end
$scope module MUL_test $end
$var wire 1 ! eqz $end
$var wire 1 " done $end
$var wire 1 # decB $end
$var wire 1 $ clrP $end
$var wire 1 % LdP $end
$var wire 1 & LdB $end
$var wire 1 ' LdA $end
$var reg 1 ( clk $end
$var reg 16 ) data_in [15:0] $end
$var reg 1 * start $end
$scope module CON $end
$var wire 1 ( clk $end
$var wire 1 * start $end
$var wire 1 ! eqz $end
$var reg 1 ' LdA $end
$var reg 1 & LdB $end
$var reg 1 % LdP $end
$var reg 1 $ clrP $end
$var reg 1 # decB $end
$var reg 1 " done $end
$var reg 3 + state [2:0] $end
$upscope $end
$scope module DP $end
$var wire 16 , Bus [15:0] $end
$var wire 1 ' LdA $end
$var wire 1 & LdB $end
$var wire 1 % LdP $end
$var wire 1 ( clk $end
$var wire 1 $ clrP $end
$var wire 16 - data_in [15:0] $end
$var wire 1 # decB $end
$var wire 1 ! eqz $end
$var wire 16 . Z [15:0] $end
$var wire 16 / Y [15:0] $end
$var wire 16 0 X [15:0] $end
$var wire 16 1 Bout [15:0] $end
$scope module A $end
$var wire 1 ( clk $end
$var wire 16 2 din [15:0] $end
$var wire 1 ' ld $end
$var reg 16 3 dout [15:0] $end
$upscope $end
$scope module AD $end
$var wire 16 4 in1 [15:0] $end
$var wire 16 5 in2 [15:0] $end
$var reg 16 6 out [15:0] $end
$upscope $end
$scope module B $end
$var wire 1 ( clk $end
$var wire 1 # dec $end
$var wire 16 7 din [15:0] $end
$var wire 1 & ld $end
$var reg 16 8 dout [15:0] $end
$upscope $end
$scope module COMP $end
$var wire 16 9 data [15:0] $end
$var wire 1 ! eqz $end
$upscope $end
$scope module P $end
$var wire 1 ( clk $end
$var wire 1 $ clr $end
$var wire 16 : din [15:0] $end
$var wire 1 % ld $end
$var reg 16 ; dout [15:0] $end
$upscope $end
$upscope $end
$upscope $end
$enddefinitions $end
#0
$dumpvars
bx ;
bx :
bx 9
bx 8
bz 7
bx 6
bx 5
bx 4
bx 3
bz 2
bx 1
bx 0
bx /
bx .
bx -
bz ,
bx +
x*
bx )
0(
x'
x&
x%
x$
x#
x"
x!
$end
#3
1*
#5
b0 +
1(
#6
0#
0$
0%
0&
0'
#10
0(
#15
b1 +
1(
#16
1'
#17
b10001 )
b10001 -
#20
0(
#25
bz 0
bz 3
bz 4
b10 +
1(
#26
1$
1&
0'
#27
b101 )
b101 -
#30
0(
#35
b11 +
bz 1
bz 8
bz 9
b0 /
b0 5
b0 ;
1(
#36
1#
0$
1%
0&
#40
0(
#45
bx /
bx 5
bx ;
bx 1
bx 8
bx 9
1(
