repeated_addition/controller.v
module controller(LdA, LdB, LdP, clrP, decB, done, clk, eqz, start);

	input clk, eqz, start;
	output reg LdA, LdB, LdP, clrP, decB, done;
	reg [2:0] state;

	parameter s0 = 3'b000, s1 = 3'b001, s2 = 3'b010, s3 = 3'b011, s4 = 3'b100;

	always @(posedge clk)
	begin
		case(state)
			s0: if (start) state <= s1;
			s1: state <= s2;
			s2: state <= s3;
			s3: #2 if (eqz) state <= s4;
			default: state <= s0;
		endcase
	end

	always @(state)
	begin
		case(state)
			s0: begin #1 LdA=0; LdB=0; LdP=0; clrP=0; decB=0; end
			s1: begin #1 LdA=1; end
			s2: begin #1 LdA=0; LdB=1; clrP=1; end
			s3: begin #1 LdB=0; LdP=1; clrP=0; decB=1; end
			s4: begin #1 done=1; LdB=0; LdP=0; decB=0; end
			default: begin #1 LdA=0; LdB=0; LdP=0; clrP=0;; decB=0; end
		endcase
	end
	
endmodule

repeated_addition/datapath.v
module MUL_datapath(eqz, LdA, LdB, LdP, clrP, decB, data_in, clk);

	input LdA, LdB, LdP, clrP, decB, clk;
	input [15:0] data_in;
	output eqz;
	wire [15:0] X, Y, Z, Bout, Bus;

  assign Bus = data_in;

	PIPO1 A(X, Bus, LdA, clk);
	PIPO2 P(Y, Z, LdP, clrP, clk);
	CNTR B(Bout, Bus, LdB, decB, clk);
	ADD AD(Z, X, Y);
	EQZ COMP(eqz, Bout);

endmodule

module PIPO1(dout, din, ld, clk);

	input [15:0] din;
	input ld, clk;
	output reg[15:0] dout;

	always @(posedge clk)
		if(ld) dout <= din;

endmodule

module PIPO2(dout, din, ld, clr, clk);

	input [15:0] din;
	input ld, clr, clk;
	output reg [15:0] dout;

	always @(posedge clk) begin
		if(clr) dout <= 16'b0;
		else if (ld) dout <= din;
	end

endmodule

module ADD(out, in1, in2);

	input[15:0] in1, in2;
	output reg [15:0] out;
	
	always @(*)
		out = in1 + in2;

endmodule

module EQZ(eqz, data);

	input [15:0] data; 
	output eqz;
	assign eqz = (data==0);

endmodule

module CNTR(dout, din, ld, dec, clk);

	input [15:0] din;
	input ld, dec,clk;
	output reg [15:0] dout;

	always @(posedge clk) begin
		if(ld) dout <= din;
		else if (dec) dout <= dout-1;
	end

endmodule

repeated_addition/testbench.vt
module MUL_test;

	reg [15:0] data_in;
	reg c;l. start;
	wire done;
	MUL_datapath DP(eqz, LdA, LdB, LdP, clrP, decB, data_in, clk);
	controller CON(LdA, LdB, LdP, clrP, decB, done, clk, eqz, start);

	initial
		begin
		clk = 1'b0;
		#3 start = 1'b1;
		#500 $finish;
	end

	always #5 clk = ~clk;

	initial begin
		#17 data_in = 17;
		#10 data_in = 5;
	end

	intial begin
		$monitor($time, "%d %b", DP.Y, done);
		$dumpfile("mul.vcd");
		$dumpvars(0, MUL_test);
	end
	
endmodule

repeated_addition/tboutput.vcd
$date
	Thu Jun  5 20:47:25 2025
$end
$version
	Icarus Verilog
$end
$timescale
	1s
$end
$scope module MUL_test $end
$var wire 1 ! eqz $end
$var wire 1 " done $end
$var wire 1 # decB $end
$var wire 1 $ clrP $end
$var wire 1 % LdP $end
$var wire 1 & LdB $end
$var wire 1 ' LdA $end
$var reg 1 ( clk $end
$var reg 16 ) data_in [15:0] $end
$var reg 1 * start $end
$scope module CON $end
$var wire 1 ( clk $end
$var wire 1 * start $end
$var wire 1 ! eqz $end
$var reg 1 ' LdA $end
$var reg 1 & LdB $end
$var reg 1 % LdP $end
$var reg 1 $ clrP $end
$var reg 1 # decB $end
$var reg 1 " done $end
$var reg 3 + state [2:0] $end
$upscope $end
$scope module DP $end
$var wire 16 , Bus [15:0] $end
$var wire 1 ' LdA $end
$var wire 1 & LdB $end
$var wire 1 % LdP $end
$var wire 1 ( clk $end
$var wire 1 $ clrP $end
$var wire 16 - data_in [15:0] $end
$var wire 1 # decB $end
$var wire 1 ! eqz $end
$var wire 16 . Z [15:0] $end
$var wire 16 / Y [15:0] $end
$var wire 16 0 X [15:0] $end
$var wire 16 1 Bout [15:0] $end
$scope module A $end
$var wire 1 ( clk $end
$var wire 16 2 din [15:0] $end
$var wire 1 ' ld $end
$var reg 16 3 dout [15:0] $end
$upscope $end
$scope module AD $end
$var wire 16 4 in1 [15:0] $end
$var wire 16 5 in2 [15:0] $end
$var reg 16 6 out [15:0] $end
$upscope $end
$scope module B $end
$var wire 1 ( clk $end
$var wire 1 # dec $end
$var wire 16 7 din [15:0] $end
$var wire 1 & ld $end
$var reg 16 8 dout [15:0] $end
$upscope $end
$scope module COMP $end
$var wire 16 9 data [15:0] $end
$var wire 1 ! eqz $end
$upscope $end
$scope module P $end
$var wire 1 ( clk $end
$var wire 1 $ clr $end
$var wire 16 : din [15:0] $end
$var wire 1 % ld $end
$var reg 16 ; dout [15:0] $end
$upscope $end
$upscope $end
$upscope $end
$enddefinitions $end
#0
$dumpvars
bx ;
bx :
bx 9
bx 8
bx 7
bx 6
bx 5
bx 4
bx 3
bx 2
bx 1
bx 0
bx /
bx .
bx -
bx ,
bx +
x*
bx )
0(
x'
x&
x%
x$
x#
x"
x!
$end
#3
1*
#5
b0 +
1(
#6
0#
0$
0%
0&
0'
#10
0(
#15
b1 +
1(
#16
1'
#17
b10001 ,
b10001 2
b10001 7
b10001 )
b10001 -
#20
0(
#25
b10001 0
b10001 3
b10001 4
b10 +
1(
#26
1$
1&
0'
#27
b101 ,
b101 2
b101 7
b101 )
b101 -
#30
0(
#35
b10001 .
b10001 6
b10001 :
b11 +
0!
b101 1
b101 8
b101 9
b0 /
b0 5
b0 ;
1(
#36
1#
0$
1%
0&
#40
0(
#45
b100010 .
b100010 6
b100010 :
b10001 /
b10001 5
b10001 ;
b100 1
b100 8
b100 9
1(
#50
0(
#55
b110011 .
b110011 6
b110011 :
b11 1
b11 8
b11 9
b100010 /
b100010 5
b100010 ;
1(
#60
0(
#65
b1000100 .
b1000100 6
b1000100 :
b110011 /
b110011 5
b110011 ;
b10 1
b10 8
b10 9
1(
#70
0(
#75
b1010101 .
b1010101 6
b1010101 :
b1 1
b1 8
b1 9
b1000100 /
b1000100 5
b1000100 ;
1(
#80
0(
#85
b1100110 .
b1100110 6
b1100110 :
b1010101 /
b1010101 5
b1010101 ;
1!
b0 1
b0 8
b0 9
1(
#87
b100 +
#88
0#
0%
1"
#90
0(
#95
b0 +
1(
#100
0(
#105
b1 +
1(
#106
1'
#110
0(
#115
b1011010 .
b1011010 6
b1011010 :
b101 0
b101 3
b101 4
b10 +
1(
#116
1$
1&
0'
#120
0(
#125
b101 .
b101 6
b101 :
b11 +
b0 /
b0 5
b0 ;
0!
b101 1
b101 8
b101 9
1(
#126
1#
0$
1%
0&
#130
0(
#135
b1010 .
b1010 6
b1010 :
b100 1
b100 8
b100 9
b101 /
b101 5
b101 ;
1(
#140
0(
#145
b1111 .
b1111 6
b1111 :
b1010 /
b1010 5
b1010 ;
b11 1
b11 8
b11 9
1(
#150
0(
#155
b10100 .
b10100 6
b10100 :
b10 1
b10 8
b10 9
b1111 /
b1111 5
b1111 ;
1(
#160
0(
#165
b11001 .
b11001 6
b11001 :
b10100 /
b10100 5
b10100 ;
b1 1
b1 8
b1 9
1(
#170
0(
#175
b11110 .
b11110 6
b11110 :
1!
b0 1
b0 8
b0 9
b11001 /
b11001 5
b11001 ;
1(
#177
b100 +
#178
0#
0%
#180
0(
#185
b0 +
1(
#190
0(
#195
b1 +
1(
#196
1'
#200
0(
#205
b10 +
1(
#206
1$
1&
0'
#210
0(
#215
b101 .
b101 6
b101 :
b11 +
0!
b101 1
b101 8
b101 9
b0 /
b0 5
b0 ;
1(
#216
1#
0$
1%
0&
#220
0(
#225
b1010 .
b1010 6
b1010 :
b101 /
b101 5
b101 ;
b100 1
b100 8
b100 9
1(
#230
0(
#235
b1111 .
b1111 6
b1111 :
b11 1
b11 8
b11 9
b1010 /
b1010 5
b1010 ;
1(
#240
0(
#245
b10100 .
b10100 6
b10100 :
b1111 /
b1111 5
b1111 ;
b10 1
b10 8
b10 9
1(
#250
0(
#255
b11001 .
b11001 6
b11001 :
b1 1
b1 8
b1 9
b10100 /
b10100 5
b10100 ;
1(
#260
0(
#265
b11110 .
b11110 6
b11110 :
b11001 /
b11001 5
b11001 ;
1!
b0 1
b0 8
b0 9
1(
#267
b100 +
#268
0#
0%
#270
0(
#275
b0 +
1(
#280
0(
#285
b1 +
1(
#286
1'
#290
0(
#295
b10 +
1(
#296
1$
1&
0'
#300
0(
#305
b101 .
b101 6
b101 :
b11 +
b0 /
b0 5
b0 ;
0!
b101 1
b101 8
b101 9
1(
#306
1#
0$
1%
0&
#310
0(
#315
b1010 .
b1010 6
b1010 :
b100 1
b100 8
b100 9
b101 /
b101 5
b101 ;
1(
#320
0(
#325
b1111 .
b1111 6
b1111 :
b1010 /
b1010 5
b1010 ;
b11 1
b11 8
b11 9
1(
#330
0(
#335
b10100 .
b10100 6
b10100 :
b10 1
b10 8
b10 9
b1111 /
b1111 5
b1111 ;
1(
#340
0(
#345
b11001 .
b11001 6
b11001 :
b10100 /
b10100 5
b10100 ;
b1 1
b1 8
b1 9
1(
#350
0(
#355
b11110 .
b11110 6
b11110 :
1!
b0 1
b0 8
b0 9
b11001 /
b11001 5
b11001 ;
1(
#357
b100 +
#358
0#
0%
#360
0(
#365
b0 +
1(
#370
0(
#375
b1 +
1(
#376
1'
#380
0(
#385
b10 +
1(
#386
1$
1&
0'
#390
0(
#395
b101 .
b101 6
b101 :
b11 +
0!
b101 1
b101 8
b101 9
b0 /
b0 5
b0 ;
1(
#396
1#
0$
1%
0&
#400
0(
#405
b1010 .
b1010 6
b1010 :
b101 /
b101 5
b101 ;
b100 1
b100 8
b100 9
1(
#410
0(
#415
b1111 .
b1111 6
b1111 :
b11 1
b11 8
b11 9
b1010 /
b1010 5
b1010 ;
1(
#420
0(
#425
b10100 .
b10100 6
b10100 :
b1111 /
b1111 5
b1111 ;
b10 1
b10 8
b10 9
1(
#430
0(
#435
b11001 .
b11001 6
b11001 :
b1 1
b1 8
b1 9
b10100 /
b10100 5
b10100 ;
1(
#440
0(
#445
b11110 .
b11110 6
b11110 :
b11001 /
b11001 5
b11001 ;
1!
b0 1
b0 8
b0 9
1(
#447
b100 +
#448
0#
0%
#450
0(
#455
b0 +
1(
#460
0(
#465
b1 +
1(
#466
1'
#470
0(
#475
b10 +
1(
#476
1$
1&
0'
#480
0(
#485
b101 .
b101 6
b101 :
b11 +
b0 /
b0 5
b0 ;
0!
b101 1
b101 8
b101 9
1(
#486
1#
0$
1%
0&
#490
0(
#495
b1010 .
b1010 6
b1010 :
b100 1
b100 8
b100 9
b101 /
b101 5
b101 ;
1(
